{
  "id": "db62b5a8-4cb9-47c4-97c2-ccb306bda5d8",
  "prevId": "00000000-0000-0000-0000-000000000000",
  "version": "7",
  "dialect": "postgresql",
  "tables": {
    "public.bandsy_conversation_participant": {
      "name": "bandsy_conversation_participant",
      "schema": "",
      "columns": {
        "id": {
          "name": "id",
          "type": "uuid",
          "primaryKey": true,
          "notNull": true,
          "default": "gen_random_uuid()"
        },
        "conversationId": {
          "name": "conversationId",
          "type": "uuid",
          "primaryKey": false,
          "notNull": true
        },
        "userId": {
          "name": "userId",
          "type": "uuid",
          "primaryKey": false,
          "notNull": true
        },
        "joinedAt": {
          "name": "joinedAt",
          "type": "timestamp with time zone",
          "primaryKey": false,
          "notNull": true,
          "default": "CURRENT_TIMESTAMP"
        }
      },
      "indexes": {
        "conversation_participants_conversation_idx": {
          "name": "conversation_participants_conversation_idx",
          "columns": [
            {
              "expression": "conversationId",
              "isExpression": false,
              "asc": true,
              "nulls": "last"
            }
          ],
          "isUnique": false,
          "concurrently": false,
          "method": "btree",
          "with": {}
        },
        "conversation_participants_user_idx": {
          "name": "conversation_participants_user_idx",
          "columns": [
            {
              "expression": "userId",
              "isExpression": false,
              "asc": true,
              "nulls": "last"
            }
          ],
          "isUnique": false,
          "concurrently": false,
          "method": "btree",
          "with": {}
        }
      },
      "foreignKeys": {
        "bandsy_conversation_participant_conversationId_bandsy_conversation_id_fk": {
          "name": "bandsy_conversation_participant_conversationId_bandsy_conversation_id_fk",
          "tableFrom": "bandsy_conversation_participant",
          "tableTo": "bandsy_conversation",
          "columnsFrom": [
            "conversationId"
          ],
          "columnsTo": [
            "id"
          ],
          "onDelete": "cascade",
          "onUpdate": "no action"
        },
        "bandsy_conversation_participant_userId_bandsy_user_id_fk": {
          "name": "bandsy_conversation_participant_userId_bandsy_user_id_fk",
          "tableFrom": "bandsy_conversation_participant",
          "tableTo": "bandsy_user",
          "columnsFrom": [
            "userId"
          ],
          "columnsTo": [
            "id"
          ],
          "onDelete": "cascade",
          "onUpdate": "no action"
        }
      },
      "compositePrimaryKeys": {},
      "uniqueConstraints": {},
      "policies": {},
      "checkConstraints": {},
      "isRLSEnabled": false
    },
    "public.bandsy_conversation": {
      "name": "bandsy_conversation",
      "schema": "",
      "columns": {
        "id": {
          "name": "id",
          "type": "uuid",
          "primaryKey": true,
          "notNull": true,
          "default": "gen_random_uuid()"
        },
        "matchId": {
          "name": "matchId",
          "type": "uuid",
          "primaryKey": false,
          "notNull": false
        },
        "groupId": {
          "name": "groupId",
          "type": "uuid",
          "primaryKey": false,
          "notNull": false
        },
        "isGroupChat": {
          "name": "isGroupChat",
          "type": "boolean",
          "primaryKey": false,
          "notNull": false,
          "default": false
        },
        "createdAt": {
          "name": "createdAt",
          "type": "timestamp with time zone",
          "primaryKey": false,
          "notNull": true,
          "default": "CURRENT_TIMESTAMP"
        },
        "updatedAt": {
          "name": "updatedAt",
          "type": "timestamp with time zone",
          "primaryKey": false,
          "notNull": false
        }
      },
      "indexes": {
        "conversations_match_idx": {
          "name": "conversations_match_idx",
          "columns": [
            {
              "expression": "matchId",
              "isExpression": false,
              "asc": true,
              "nulls": "last"
            }
          ],
          "isUnique": false,
          "concurrently": false,
          "method": "btree",
          "with": {}
        },
        "conversations_group_idx": {
          "name": "conversations_group_idx",
          "columns": [
            {
              "expression": "groupId",
              "isExpression": false,
              "asc": true,
              "nulls": "last"
            }
          ],
          "isUnique": false,
          "concurrently": false,
          "method": "btree",
          "with": {}
        }
      },
      "foreignKeys": {
        "bandsy_conversation_matchId_bandsy_match_id_fk": {
          "name": "bandsy_conversation_matchId_bandsy_match_id_fk",
          "tableFrom": "bandsy_conversation",
          "tableTo": "bandsy_match",
          "columnsFrom": [
            "matchId"
          ],
          "columnsTo": [
            "id"
          ],
          "onDelete": "cascade",
          "onUpdate": "no action"
        },
        "bandsy_conversation_groupId_bandsy_group_id_fk": {
          "name": "bandsy_conversation_groupId_bandsy_group_id_fk",
          "tableFrom": "bandsy_conversation",
          "tableTo": "bandsy_group",
          "columnsFrom": [
            "groupId"
          ],
          "columnsTo": [
            "id"
          ],
          "onDelete": "cascade",
          "onUpdate": "no action"
        }
      },
      "compositePrimaryKeys": {},
      "uniqueConstraints": {},
      "policies": {},
      "checkConstraints": {},
      "isRLSEnabled": false
    },
    "public.bandsy_event": {
      "name": "bandsy_event",
      "schema": "",
      "columns": {
        "id": {
          "name": "id",
          "type": "uuid",
          "primaryKey": true,
          "notNull": true,
          "default": "gen_random_uuid()"
        },
        "groupId": {
          "name": "groupId",
          "type": "uuid",
          "primaryKey": false,
          "notNull": true
        },
        "title": {
          "name": "title",
          "type": "varchar(200)",
          "primaryKey": false,
          "notNull": true
        },
        "description": {
          "name": "description",
          "type": "text",
          "primaryKey": false,
          "notNull": false
        },
        "venue": {
          "name": "venue",
          "type": "varchar(200)",
          "primaryKey": false,
          "notNull": false
        },
        "address": {
          "name": "address",
          "type": "text",
          "primaryKey": false,
          "notNull": false
        },
        "startDate": {
          "name": "startDate",
          "type": "timestamp with time zone",
          "primaryKey": false,
          "notNull": true
        },
        "endDate": {
          "name": "endDate",
          "type": "timestamp with time zone",
          "primaryKey": false,
          "notNull": false
        },
        "isPublic": {
          "name": "isPublic",
          "type": "boolean",
          "primaryKey": false,
          "notNull": false,
          "default": true
        },
        "maxAttendees": {
          "name": "maxAttendees",
          "type": "integer",
          "primaryKey": false,
          "notNull": false
        },
        "createdAt": {
          "name": "createdAt",
          "type": "timestamp with time zone",
          "primaryKey": false,
          "notNull": true,
          "default": "CURRENT_TIMESTAMP"
        }
      },
      "indexes": {
        "events_group_idx": {
          "name": "events_group_idx",
          "columns": [
            {
              "expression": "groupId",
              "isExpression": false,
              "asc": true,
              "nulls": "last"
            }
          ],
          "isUnique": false,
          "concurrently": false,
          "method": "btree",
          "with": {}
        },
        "events_date_idx": {
          "name": "events_date_idx",
          "columns": [
            {
              "expression": "startDate",
              "isExpression": false,
              "asc": true,
              "nulls": "last"
            }
          ],
          "isUnique": false,
          "concurrently": false,
          "method": "btree",
          "with": {}
        }
      },
      "foreignKeys": {
        "bandsy_event_groupId_bandsy_group_id_fk": {
          "name": "bandsy_event_groupId_bandsy_group_id_fk",
          "tableFrom": "bandsy_event",
          "tableTo": "bandsy_group",
          "columnsFrom": [
            "groupId"
          ],
          "columnsTo": [
            "id"
          ],
          "onDelete": "cascade",
          "onUpdate": "no action"
        }
      },
      "compositePrimaryKeys": {},
      "uniqueConstraints": {},
      "policies": {},
      "checkConstraints": {},
      "isRLSEnabled": false
    },
    "public.bandsy_genre": {
      "name": "bandsy_genre",
      "schema": "",
      "columns": {
        "id": {
          "name": "id",
          "type": "uuid",
          "primaryKey": true,
          "notNull": true,
          "default": "gen_random_uuid()"
        },
        "name": {
          "name": "name",
          "type": "varchar(100)",
          "primaryKey": false,
          "notNull": true
        },
        "parentGenreId": {
          "name": "parentGenreId",
          "type": "uuid",
          "primaryKey": false,
          "notNull": false
        },
        "createdAt": {
          "name": "createdAt",
          "type": "timestamp with time zone",
          "primaryKey": false,
          "notNull": true,
          "default": "CURRENT_TIMESTAMP"
        }
      },
      "indexes": {},
      "foreignKeys": {},
      "compositePrimaryKeys": {},
      "uniqueConstraints": {
        "bandsy_genre_name_unique": {
          "name": "bandsy_genre_name_unique",
          "nullsNotDistinct": false,
          "columns": [
            "name"
          ]
        }
      },
      "policies": {},
      "checkConstraints": {},
      "isRLSEnabled": false
    },
    "public.bandsy_group_genre": {
      "name": "bandsy_group_genre",
      "schema": "",
      "columns": {
        "id": {
          "name": "id",
          "type": "uuid",
          "primaryKey": true,
          "notNull": true,
          "default": "gen_random_uuid()"
        },
        "groupId": {
          "name": "groupId",
          "type": "uuid",
          "primaryKey": false,
          "notNull": true
        },
        "genreId": {
          "name": "genreId",
          "type": "uuid",
          "primaryKey": false,
          "notNull": true
        },
        "createdAt": {
          "name": "createdAt",
          "type": "timestamp with time zone",
          "primaryKey": false,
          "notNull": true,
          "default": "CURRENT_TIMESTAMP"
        }
      },
      "indexes": {
        "group_genres_group_idx": {
          "name": "group_genres_group_idx",
          "columns": [
            {
              "expression": "groupId",
              "isExpression": false,
              "asc": true,
              "nulls": "last"
            }
          ],
          "isUnique": false,
          "concurrently": false,
          "method": "btree",
          "with": {}
        },
        "group_genres_genre_idx": {
          "name": "group_genres_genre_idx",
          "columns": [
            {
              "expression": "genreId",
              "isExpression": false,
              "asc": true,
              "nulls": "last"
            }
          ],
          "isUnique": false,
          "concurrently": false,
          "method": "btree",
          "with": {}
        }
      },
      "foreignKeys": {
        "bandsy_group_genre_groupId_bandsy_group_id_fk": {
          "name": "bandsy_group_genre_groupId_bandsy_group_id_fk",
          "tableFrom": "bandsy_group_genre",
          "tableTo": "bandsy_group",
          "columnsFrom": [
            "groupId"
          ],
          "columnsTo": [
            "id"
          ],
          "onDelete": "cascade",
          "onUpdate": "no action"
        },
        "bandsy_group_genre_genreId_bandsy_genre_id_fk": {
          "name": "bandsy_group_genre_genreId_bandsy_genre_id_fk",
          "tableFrom": "bandsy_group_genre",
          "tableTo": "bandsy_genre",
          "columnsFrom": [
            "genreId"
          ],
          "columnsTo": [
            "id"
          ],
          "onDelete": "cascade",
          "onUpdate": "no action"
        }
      },
      "compositePrimaryKeys": {},
      "uniqueConstraints": {},
      "policies": {},
      "checkConstraints": {},
      "isRLSEnabled": false
    },
    "public.bandsy_group_member": {
      "name": "bandsy_group_member",
      "schema": "",
      "columns": {
        "id": {
          "name": "id",
          "type": "uuid",
          "primaryKey": true,
          "notNull": true,
          "default": "gen_random_uuid()"
        },
        "groupId": {
          "name": "groupId",
          "type": "uuid",
          "primaryKey": false,
          "notNull": true
        },
        "userId": {
          "name": "userId",
          "type": "uuid",
          "primaryKey": false,
          "notNull": true
        },
        "role": {
          "name": "role",
          "type": "group_role",
          "typeSchema": "public",
          "primaryKey": false,
          "notNull": true,
          "default": "'member'"
        },
        "instrumentId": {
          "name": "instrumentId",
          "type": "uuid",
          "primaryKey": false,
          "notNull": false
        },
        "joinedAt": {
          "name": "joinedAt",
          "type": "timestamp with time zone",
          "primaryKey": false,
          "notNull": true,
          "default": "CURRENT_TIMESTAMP"
        }
      },
      "indexes": {
        "group_members_group_idx": {
          "name": "group_members_group_idx",
          "columns": [
            {
              "expression": "groupId",
              "isExpression": false,
              "asc": true,
              "nulls": "last"
            }
          ],
          "isUnique": false,
          "concurrently": false,
          "method": "btree",
          "with": {}
        },
        "group_members_user_idx": {
          "name": "group_members_user_idx",
          "columns": [
            {
              "expression": "userId",
              "isExpression": false,
              "asc": true,
              "nulls": "last"
            }
          ],
          "isUnique": false,
          "concurrently": false,
          "method": "btree",
          "with": {}
        }
      },
      "foreignKeys": {
        "bandsy_group_member_groupId_bandsy_group_id_fk": {
          "name": "bandsy_group_member_groupId_bandsy_group_id_fk",
          "tableFrom": "bandsy_group_member",
          "tableTo": "bandsy_group",
          "columnsFrom": [
            "groupId"
          ],
          "columnsTo": [
            "id"
          ],
          "onDelete": "cascade",
          "onUpdate": "no action"
        },
        "bandsy_group_member_userId_bandsy_user_id_fk": {
          "name": "bandsy_group_member_userId_bandsy_user_id_fk",
          "tableFrom": "bandsy_group_member",
          "tableTo": "bandsy_user",
          "columnsFrom": [
            "userId"
          ],
          "columnsTo": [
            "id"
          ],
          "onDelete": "cascade",
          "onUpdate": "no action"
        },
        "bandsy_group_member_instrumentId_bandsy_instrument_id_fk": {
          "name": "bandsy_group_member_instrumentId_bandsy_instrument_id_fk",
          "tableFrom": "bandsy_group_member",
          "tableTo": "bandsy_instrument",
          "columnsFrom": [
            "instrumentId"
          ],
          "columnsTo": [
            "id"
          ],
          "onDelete": "no action",
          "onUpdate": "no action"
        }
      },
      "compositePrimaryKeys": {},
      "uniqueConstraints": {},
      "policies": {},
      "checkConstraints": {},
      "isRLSEnabled": false
    },
    "public.bandsy_group": {
      "name": "bandsy_group",
      "schema": "",
      "columns": {
        "id": {
          "name": "id",
          "type": "uuid",
          "primaryKey": true,
          "notNull": true,
          "default": "gen_random_uuid()"
        },
        "name": {
          "name": "name",
          "type": "varchar(200)",
          "primaryKey": false,
          "notNull": true
        },
        "description": {
          "name": "description",
          "type": "text",
          "primaryKey": false,
          "notNull": false
        },
        "imageUrl": {
          "name": "imageUrl",
          "type": "varchar(500)",
          "primaryKey": false,
          "notNull": false
        },
        "isActive": {
          "name": "isActive",
          "type": "boolean",
          "primaryKey": false,
          "notNull": false,
          "default": true
        },
        "maxMembers": {
          "name": "maxMembers",
          "type": "integer",
          "primaryKey": false,
          "notNull": false,
          "default": 10
        },
        "createdAt": {
          "name": "createdAt",
          "type": "timestamp with time zone",
          "primaryKey": false,
          "notNull": true,
          "default": "CURRENT_TIMESTAMP"
        },
        "updatedAt": {
          "name": "updatedAt",
          "type": "timestamp with time zone",
          "primaryKey": false,
          "notNull": false
        }
      },
      "indexes": {},
      "foreignKeys": {},
      "compositePrimaryKeys": {},
      "uniqueConstraints": {},
      "policies": {},
      "checkConstraints": {},
      "isRLSEnabled": false
    },
    "public.bandsy_instrument": {
      "name": "bandsy_instrument",
      "schema": "",
      "columns": {
        "id": {
          "name": "id",
          "type": "uuid",
          "primaryKey": true,
          "notNull": true,
          "default": "gen_random_uuid()"
        },
        "name": {
          "name": "name",
          "type": "varchar(100)",
          "primaryKey": false,
          "notNull": true
        },
        "category": {
          "name": "category",
          "type": "varchar(50)",
          "primaryKey": false,
          "notNull": false
        },
        "createdAt": {
          "name": "createdAt",
          "type": "timestamp with time zone",
          "primaryKey": false,
          "notNull": true,
          "default": "CURRENT_TIMESTAMP"
        }
      },
      "indexes": {},
      "foreignKeys": {},
      "compositePrimaryKeys": {},
      "uniqueConstraints": {
        "bandsy_instrument_name_unique": {
          "name": "bandsy_instrument_name_unique",
          "nullsNotDistinct": false,
          "columns": [
            "name"
          ]
        }
      },
      "policies": {},
      "checkConstraints": {},
      "isRLSEnabled": false
    },
    "public.bandsy_match": {
      "name": "bandsy_match",
      "schema": "",
      "columns": {
        "id": {
          "name": "id",
          "type": "uuid",
          "primaryKey": true,
          "notNull": true,
          "default": "gen_random_uuid()"
        },
        "initiatorId": {
          "name": "initiatorId",
          "type": "uuid",
          "primaryKey": false,
          "notNull": true
        },
        "targetId": {
          "name": "targetId",
          "type": "uuid",
          "primaryKey": false,
          "notNull": true
        },
        "status": {
          "name": "status",
          "type": "match_status",
          "typeSchema": "public",
          "primaryKey": false,
          "notNull": true
        },
        "initiatorMessage": {
          "name": "initiatorMessage",
          "type": "text",
          "primaryKey": false,
          "notNull": false
        },
        "matchedAt": {
          "name": "matchedAt",
          "type": "timestamp with time zone",
          "primaryKey": false,
          "notNull": false
        },
        "createdAt": {
          "name": "createdAt",
          "type": "timestamp with time zone",
          "primaryKey": false,
          "notNull": true,
          "default": "CURRENT_TIMESTAMP"
        }
      },
      "indexes": {
        "matches_initiator_idx": {
          "name": "matches_initiator_idx",
          "columns": [
            {
              "expression": "initiatorId",
              "isExpression": false,
              "asc": true,
              "nulls": "last"
            }
          ],
          "isUnique": false,
          "concurrently": false,
          "method": "btree",
          "with": {}
        },
        "matches_target_idx": {
          "name": "matches_target_idx",
          "columns": [
            {
              "expression": "targetId",
              "isExpression": false,
              "asc": true,
              "nulls": "last"
            }
          ],
          "isUnique": false,
          "concurrently": false,
          "method": "btree",
          "with": {}
        },
        "matches_status_idx": {
          "name": "matches_status_idx",
          "columns": [
            {
              "expression": "status",
              "isExpression": false,
              "asc": true,
              "nulls": "last"
            }
          ],
          "isUnique": false,
          "concurrently": false,
          "method": "btree",
          "with": {}
        }
      },
      "foreignKeys": {
        "bandsy_match_initiatorId_bandsy_user_id_fk": {
          "name": "bandsy_match_initiatorId_bandsy_user_id_fk",
          "tableFrom": "bandsy_match",
          "tableTo": "bandsy_user",
          "columnsFrom": [
            "initiatorId"
          ],
          "columnsTo": [
            "id"
          ],
          "onDelete": "cascade",
          "onUpdate": "no action"
        },
        "bandsy_match_targetId_bandsy_user_id_fk": {
          "name": "bandsy_match_targetId_bandsy_user_id_fk",
          "tableFrom": "bandsy_match",
          "tableTo": "bandsy_user",
          "columnsFrom": [
            "targetId"
          ],
          "columnsTo": [
            "id"
          ],
          "onDelete": "cascade",
          "onUpdate": "no action"
        }
      },
      "compositePrimaryKeys": {},
      "uniqueConstraints": {},
      "policies": {},
      "checkConstraints": {},
      "isRLSEnabled": false
    },
    "public.bandsy_media_sample": {
      "name": "bandsy_media_sample",
      "schema": "",
      "columns": {
        "id": {
          "name": "id",
          "type": "uuid",
          "primaryKey": true,
          "notNull": true,
          "default": "gen_random_uuid()"
        },
        "userId": {
          "name": "userId",
          "type": "uuid",
          "primaryKey": false,
          "notNull": true
        },
        "instrumentId": {
          "name": "instrumentId",
          "type": "uuid",
          "primaryKey": false,
          "notNull": false
        },
        "title": {
          "name": "title",
          "type": "varchar(200)",
          "primaryKey": false,
          "notNull": true
        },
        "description": {
          "name": "description",
          "type": "text",
          "primaryKey": false,
          "notNull": false
        },
        "fileUrl": {
          "name": "fileUrl",
          "type": "varchar(500)",
          "primaryKey": false,
          "notNull": true
        },
        "fileType": {
          "name": "fileType",
          "type": "varchar(50)",
          "primaryKey": false,
          "notNull": true
        },
        "duration": {
          "name": "duration",
          "type": "integer",
          "primaryKey": false,
          "notNull": false
        },
        "metadata": {
          "name": "metadata",
          "type": "json",
          "primaryKey": false,
          "notNull": false
        },
        "isPublic": {
          "name": "isPublic",
          "type": "boolean",
          "primaryKey": false,
          "notNull": false,
          "default": true
        },
        "createdAt": {
          "name": "createdAt",
          "type": "timestamp with time zone",
          "primaryKey": false,
          "notNull": true,
          "default": "CURRENT_TIMESTAMP"
        }
      },
      "indexes": {
        "media_samples_user_idx": {
          "name": "media_samples_user_idx",
          "columns": [
            {
              "expression": "userId",
              "isExpression": false,
              "asc": true,
              "nulls": "last"
            }
          ],
          "isUnique": false,
          "concurrently": false,
          "method": "btree",
          "with": {}
        },
        "media_samples_instrument_idx": {
          "name": "media_samples_instrument_idx",
          "columns": [
            {
              "expression": "instrumentId",
              "isExpression": false,
              "asc": true,
              "nulls": "last"
            }
          ],
          "isUnique": false,
          "concurrently": false,
          "method": "btree",
          "with": {}
        }
      },
      "foreignKeys": {
        "bandsy_media_sample_userId_bandsy_user_id_fk": {
          "name": "bandsy_media_sample_userId_bandsy_user_id_fk",
          "tableFrom": "bandsy_media_sample",
          "tableTo": "bandsy_user",
          "columnsFrom": [
            "userId"
          ],
          "columnsTo": [
            "id"
          ],
          "onDelete": "cascade",
          "onUpdate": "no action"
        },
        "bandsy_media_sample_instrumentId_bandsy_instrument_id_fk": {
          "name": "bandsy_media_sample_instrumentId_bandsy_instrument_id_fk",
          "tableFrom": "bandsy_media_sample",
          "tableTo": "bandsy_instrument",
          "columnsFrom": [
            "instrumentId"
          ],
          "columnsTo": [
            "id"
          ],
          "onDelete": "no action",
          "onUpdate": "no action"
        }
      },
      "compositePrimaryKeys": {},
      "uniqueConstraints": {},
      "policies": {},
      "checkConstraints": {},
      "isRLSEnabled": false
    },
    "public.bandsy_message": {
      "name": "bandsy_message",
      "schema": "",
      "columns": {
        "id": {
          "name": "id",
          "type": "uuid",
          "primaryKey": true,
          "notNull": true,
          "default": "gen_random_uuid()"
        },
        "conversationId": {
          "name": "conversationId",
          "type": "uuid",
          "primaryKey": false,
          "notNull": true
        },
        "senderId": {
          "name": "senderId",
          "type": "uuid",
          "primaryKey": false,
          "notNull": true
        },
        "type": {
          "name": "type",
          "type": "message_type",
          "typeSchema": "public",
          "primaryKey": false,
          "notNull": true
        },
        "content": {
          "name": "content",
          "type": "text",
          "primaryKey": false,
          "notNull": false
        },
        "fileUrl": {
          "name": "fileUrl",
          "type": "varchar(500)",
          "primaryKey": false,
          "notNull": false
        },
        "metadata": {
          "name": "metadata",
          "type": "json",
          "primaryKey": false,
          "notNull": false
        },
        "isRead": {
          "name": "isRead",
          "type": "boolean",
          "primaryKey": false,
          "notNull": false,
          "default": false
        },
        "createdAt": {
          "name": "createdAt",
          "type": "timestamp with time zone",
          "primaryKey": false,
          "notNull": true,
          "default": "CURRENT_TIMESTAMP"
        }
      },
      "indexes": {
        "messages_conversation_idx": {
          "name": "messages_conversation_idx",
          "columns": [
            {
              "expression": "conversationId",
              "isExpression": false,
              "asc": true,
              "nulls": "last"
            }
          ],
          "isUnique": false,
          "concurrently": false,
          "method": "btree",
          "with": {}
        },
        "messages_sender_idx": {
          "name": "messages_sender_idx",
          "columns": [
            {
              "expression": "senderId",
              "isExpression": false,
              "asc": true,
              "nulls": "last"
            }
          ],
          "isUnique": false,
          "concurrently": false,
          "method": "btree",
          "with": {}
        },
        "messages_created_at_idx": {
          "name": "messages_created_at_idx",
          "columns": [
            {
              "expression": "createdAt",
              "isExpression": false,
              "asc": true,
              "nulls": "last"
            }
          ],
          "isUnique": false,
          "concurrently": false,
          "method": "btree",
          "with": {}
        }
      },
      "foreignKeys": {
        "bandsy_message_conversationId_bandsy_conversation_id_fk": {
          "name": "bandsy_message_conversationId_bandsy_conversation_id_fk",
          "tableFrom": "bandsy_message",
          "tableTo": "bandsy_conversation",
          "columnsFrom": [
            "conversationId"
          ],
          "columnsTo": [
            "id"
          ],
          "onDelete": "cascade",
          "onUpdate": "no action"
        },
        "bandsy_message_senderId_bandsy_user_id_fk": {
          "name": "bandsy_message_senderId_bandsy_user_id_fk",
          "tableFrom": "bandsy_message",
          "tableTo": "bandsy_user",
          "columnsFrom": [
            "senderId"
          ],
          "columnsTo": [
            "id"
          ],
          "onDelete": "cascade",
          "onUpdate": "no action"
        }
      },
      "compositePrimaryKeys": {},
      "uniqueConstraints": {},
      "policies": {},
      "checkConstraints": {},
      "isRLSEnabled": false
    },
    "public.bandsy_subscription": {
      "name": "bandsy_subscription",
      "schema": "",
      "columns": {
        "id": {
          "name": "id",
          "type": "uuid",
          "primaryKey": true,
          "notNull": true,
          "default": "gen_random_uuid()"
        },
        "userId": {
          "name": "userId",
          "type": "uuid",
          "primaryKey": false,
          "notNull": true
        },
        "planType": {
          "name": "planType",
          "type": "varchar(50)",
          "primaryKey": false,
          "notNull": true
        },
        "status": {
          "name": "status",
          "type": "varchar(20)",
          "primaryKey": false,
          "notNull": true
        },
        "startDate": {
          "name": "startDate",
          "type": "timestamp with time zone",
          "primaryKey": false,
          "notNull": true
        },
        "endDate": {
          "name": "endDate",
          "type": "timestamp with time zone",
          "primaryKey": false,
          "notNull": false
        },
        "createdAt": {
          "name": "createdAt",
          "type": "timestamp with time zone",
          "primaryKey": false,
          "notNull": true,
          "default": "CURRENT_TIMESTAMP"
        }
      },
      "indexes": {
        "subscriptions_user_idx": {
          "name": "subscriptions_user_idx",
          "columns": [
            {
              "expression": "userId",
              "isExpression": false,
              "asc": true,
              "nulls": "last"
            }
          ],
          "isUnique": false,
          "concurrently": false,
          "method": "btree",
          "with": {}
        },
        "subscriptions_status_idx": {
          "name": "subscriptions_status_idx",
          "columns": [
            {
              "expression": "status",
              "isExpression": false,
              "asc": true,
              "nulls": "last"
            }
          ],
          "isUnique": false,
          "concurrently": false,
          "method": "btree",
          "with": {}
        }
      },
      "foreignKeys": {
        "bandsy_subscription_userId_bandsy_user_id_fk": {
          "name": "bandsy_subscription_userId_bandsy_user_id_fk",
          "tableFrom": "bandsy_subscription",
          "tableTo": "bandsy_user",
          "columnsFrom": [
            "userId"
          ],
          "columnsTo": [
            "id"
          ],
          "onDelete": "cascade",
          "onUpdate": "no action"
        }
      },
      "compositePrimaryKeys": {},
      "uniqueConstraints": {},
      "policies": {},
      "checkConstraints": {},
      "isRLSEnabled": false
    },
    "public.bandsy_swipe_history": {
      "name": "bandsy_swipe_history",
      "schema": "",
      "columns": {
        "id": {
          "name": "id",
          "type": "uuid",
          "primaryKey": true,
          "notNull": true,
          "default": "gen_random_uuid()"
        },
        "swiperId": {
          "name": "swiperId",
          "type": "uuid",
          "primaryKey": false,
          "notNull": true
        },
        "targetId": {
          "name": "targetId",
          "type": "uuid",
          "primaryKey": false,
          "notNull": true
        },
        "action": {
          "name": "action",
          "type": "varchar(20)",
          "primaryKey": false,
          "notNull": true
        },
        "createdAt": {
          "name": "createdAt",
          "type": "timestamp with time zone",
          "primaryKey": false,
          "notNull": true,
          "default": "CURRENT_TIMESTAMP"
        }
      },
      "indexes": {
        "swipe_history_swiper_idx": {
          "name": "swipe_history_swiper_idx",
          "columns": [
            {
              "expression": "swiperId",
              "isExpression": false,
              "asc": true,
              "nulls": "last"
            }
          ],
          "isUnique": false,
          "concurrently": false,
          "method": "btree",
          "with": {}
        },
        "swipe_history_target_idx": {
          "name": "swipe_history_target_idx",
          "columns": [
            {
              "expression": "targetId",
              "isExpression": false,
              "asc": true,
              "nulls": "last"
            }
          ],
          "isUnique": false,
          "concurrently": false,
          "method": "btree",
          "with": {}
        },
        "swipe_history_created_at_idx": {
          "name": "swipe_history_created_at_idx",
          "columns": [
            {
              "expression": "createdAt",
              "isExpression": false,
              "asc": true,
              "nulls": "last"
            }
          ],
          "isUnique": false,
          "concurrently": false,
          "method": "btree",
          "with": {}
        }
      },
      "foreignKeys": {
        "bandsy_swipe_history_swiperId_bandsy_user_id_fk": {
          "name": "bandsy_swipe_history_swiperId_bandsy_user_id_fk",
          "tableFrom": "bandsy_swipe_history",
          "tableTo": "bandsy_user",
          "columnsFrom": [
            "swiperId"
          ],
          "columnsTo": [
            "id"
          ],
          "onDelete": "cascade",
          "onUpdate": "no action"
        },
        "bandsy_swipe_history_targetId_bandsy_user_id_fk": {
          "name": "bandsy_swipe_history_targetId_bandsy_user_id_fk",
          "tableFrom": "bandsy_swipe_history",
          "tableTo": "bandsy_user",
          "columnsFrom": [
            "targetId"
          ],
          "columnsTo": [
            "id"
          ],
          "onDelete": "cascade",
          "onUpdate": "no action"
        }
      },
      "compositePrimaryKeys": {},
      "uniqueConstraints": {},
      "policies": {},
      "checkConstraints": {},
      "isRLSEnabled": false
    },
    "public.bandsy_user_genre": {
      "name": "bandsy_user_genre",
      "schema": "",
      "columns": {
        "id": {
          "name": "id",
          "type": "uuid",
          "primaryKey": true,
          "notNull": true,
          "default": "gen_random_uuid()"
        },
        "userId": {
          "name": "userId",
          "type": "uuid",
          "primaryKey": false,
          "notNull": true
        },
        "genreId": {
          "name": "genreId",
          "type": "uuid",
          "primaryKey": false,
          "notNull": true
        },
        "preference": {
          "name": "preference",
          "type": "integer",
          "primaryKey": false,
          "notNull": false,
          "default": 1
        },
        "createdAt": {
          "name": "createdAt",
          "type": "timestamp with time zone",
          "primaryKey": false,
          "notNull": true,
          "default": "CURRENT_TIMESTAMP"
        }
      },
      "indexes": {
        "user_genres_user_idx": {
          "name": "user_genres_user_idx",
          "columns": [
            {
              "expression": "userId",
              "isExpression": false,
              "asc": true,
              "nulls": "last"
            }
          ],
          "isUnique": false,
          "concurrently": false,
          "method": "btree",
          "with": {}
        },
        "user_genres_genre_idx": {
          "name": "user_genres_genre_idx",
          "columns": [
            {
              "expression": "genreId",
              "isExpression": false,
              "asc": true,
              "nulls": "last"
            }
          ],
          "isUnique": false,
          "concurrently": false,
          "method": "btree",
          "with": {}
        }
      },
      "foreignKeys": {
        "bandsy_user_genre_userId_bandsy_user_id_fk": {
          "name": "bandsy_user_genre_userId_bandsy_user_id_fk",
          "tableFrom": "bandsy_user_genre",
          "tableTo": "bandsy_user",
          "columnsFrom": [
            "userId"
          ],
          "columnsTo": [
            "id"
          ],
          "onDelete": "cascade",
          "onUpdate": "no action"
        },
        "bandsy_user_genre_genreId_bandsy_genre_id_fk": {
          "name": "bandsy_user_genre_genreId_bandsy_genre_id_fk",
          "tableFrom": "bandsy_user_genre",
          "tableTo": "bandsy_genre",
          "columnsFrom": [
            "genreId"
          ],
          "columnsTo": [
            "id"
          ],
          "onDelete": "cascade",
          "onUpdate": "no action"
        }
      },
      "compositePrimaryKeys": {},
      "uniqueConstraints": {},
      "policies": {},
      "checkConstraints": {},
      "isRLSEnabled": false
    },
    "public.bandsy_user_instrument": {
      "name": "bandsy_user_instrument",
      "schema": "",
      "columns": {
        "id": {
          "name": "id",
          "type": "uuid",
          "primaryKey": true,
          "notNull": true,
          "default": "gen_random_uuid()"
        },
        "userId": {
          "name": "userId",
          "type": "uuid",
          "primaryKey": false,
          "notNull": true
        },
        "instrumentId": {
          "name": "instrumentId",
          "type": "uuid",
          "primaryKey": false,
          "notNull": true
        },
        "skillLevel": {
          "name": "skillLevel",
          "type": "skill_level",
          "typeSchema": "public",
          "primaryKey": false,
          "notNull": true
        },
        "yearsOfExperience": {
          "name": "yearsOfExperience",
          "type": "integer",
          "primaryKey": false,
          "notNull": false
        },
        "isPrimary": {
          "name": "isPrimary",
          "type": "boolean",
          "primaryKey": false,
          "notNull": false,
          "default": false
        },
        "createdAt": {
          "name": "createdAt",
          "type": "timestamp with time zone",
          "primaryKey": false,
          "notNull": true,
          "default": "CURRENT_TIMESTAMP"
        }
      },
      "indexes": {
        "user_instruments_user_idx": {
          "name": "user_instruments_user_idx",
          "columns": [
            {
              "expression": "userId",
              "isExpression": false,
              "asc": true,
              "nulls": "last"
            }
          ],
          "isUnique": false,
          "concurrently": false,
          "method": "btree",
          "with": {}
        },
        "user_instruments_instrument_idx": {
          "name": "user_instruments_instrument_idx",
          "columns": [
            {
              "expression": "instrumentId",
              "isExpression": false,
              "asc": true,
              "nulls": "last"
            }
          ],
          "isUnique": false,
          "concurrently": false,
          "method": "btree",
          "with": {}
        }
      },
      "foreignKeys": {
        "bandsy_user_instrument_userId_bandsy_user_id_fk": {
          "name": "bandsy_user_instrument_userId_bandsy_user_id_fk",
          "tableFrom": "bandsy_user_instrument",
          "tableTo": "bandsy_user",
          "columnsFrom": [
            "userId"
          ],
          "columnsTo": [
            "id"
          ],
          "onDelete": "cascade",
          "onUpdate": "no action"
        },
        "bandsy_user_instrument_instrumentId_bandsy_instrument_id_fk": {
          "name": "bandsy_user_instrument_instrumentId_bandsy_instrument_id_fk",
          "tableFrom": "bandsy_user_instrument",
          "tableTo": "bandsy_instrument",
          "columnsFrom": [
            "instrumentId"
          ],
          "columnsTo": [
            "id"
          ],
          "onDelete": "cascade",
          "onUpdate": "no action"
        }
      },
      "compositePrimaryKeys": {},
      "uniqueConstraints": {},
      "policies": {},
      "checkConstraints": {},
      "isRLSEnabled": false
    },
    "public.bandsy_user_preference": {
      "name": "bandsy_user_preference",
      "schema": "",
      "columns": {
        "id": {
          "name": "id",
          "type": "uuid",
          "primaryKey": true,
          "notNull": true,
          "default": "gen_random_uuid()"
        },
        "userId": {
          "name": "userId",
          "type": "uuid",
          "primaryKey": false,
          "notNull": true
        },
        "maxDistance": {
          "name": "maxDistance",
          "type": "integer",
          "primaryKey": false,
          "notNull": false,
          "default": 50
        },
        "minAge": {
          "name": "minAge",
          "type": "integer",
          "primaryKey": false,
          "notNull": false
        },
        "maxAge": {
          "name": "maxAge",
          "type": "integer",
          "primaryKey": false,
          "notNull": false
        },
        "skillLevels": {
          "name": "skillLevels",
          "type": "json",
          "primaryKey": false,
          "notNull": false
        },
        "isActive": {
          "name": "isActive",
          "type": "boolean",
          "primaryKey": false,
          "notNull": false,
          "default": true
        },
        "createdAt": {
          "name": "createdAt",
          "type": "timestamp with time zone",
          "primaryKey": false,
          "notNull": true,
          "default": "CURRENT_TIMESTAMP"
        },
        "updatedAt": {
          "name": "updatedAt",
          "type": "timestamp with time zone",
          "primaryKey": false,
          "notNull": false
        }
      },
      "indexes": {
        "user_preferences_user_idx": {
          "name": "user_preferences_user_idx",
          "columns": [
            {
              "expression": "userId",
              "isExpression": false,
              "asc": true,
              "nulls": "last"
            }
          ],
          "isUnique": false,
          "concurrently": false,
          "method": "btree",
          "with": {}
        }
      },
      "foreignKeys": {
        "bandsy_user_preference_userId_bandsy_user_id_fk": {
          "name": "bandsy_user_preference_userId_bandsy_user_id_fk",
          "tableFrom": "bandsy_user_preference",
          "tableTo": "bandsy_user",
          "columnsFrom": [
            "userId"
          ],
          "columnsTo": [
            "id"
          ],
          "onDelete": "cascade",
          "onUpdate": "no action"
        }
      },
      "compositePrimaryKeys": {},
      "uniqueConstraints": {
        "bandsy_user_preference_userId_unique": {
          "name": "bandsy_user_preference_userId_unique",
          "nullsNotDistinct": false,
          "columns": [
            "userId"
          ]
        }
      },
      "policies": {},
      "checkConstraints": {},
      "isRLSEnabled": false
    },
    "public.bandsy_user": {
      "name": "bandsy_user",
      "schema": "",
      "columns": {
        "id": {
          "name": "id",
          "type": "uuid",
          "primaryKey": true,
          "notNull": true,
          "default": "gen_random_uuid()"
        },
        "clerkId": {
          "name": "clerkId",
          "type": "varchar(255)",
          "primaryKey": false,
          "notNull": true
        },
        "username": {
          "name": "username",
          "type": "varchar(50)",
          "primaryKey": false,
          "notNull": true
        },
        "displayName": {
          "name": "displayName",
          "type": "varchar(100)",
          "primaryKey": false,
          "notNull": true
        },
        "bio": {
          "name": "bio",
          "type": "text",
          "primaryKey": false,
          "notNull": false
        },
        "age": {
          "name": "age",
          "type": "integer",
          "primaryKey": false,
          "notNull": false
        },
        "showAge": {
          "name": "showAge",
          "type": "boolean",
          "primaryKey": false,
          "notNull": false,
          "default": false
        },
        "city": {
          "name": "city",
          "type": "varchar(100)",
          "primaryKey": false,
          "notNull": false
        },
        "region": {
          "name": "region",
          "type": "varchar(100)",
          "primaryKey": false,
          "notNull": false
        },
        "country": {
          "name": "country",
          "type": "varchar(100)",
          "primaryKey": false,
          "notNull": false
        },
        "latitude": {
          "name": "latitude",
          "type": "numeric(10, 8)",
          "primaryKey": false,
          "notNull": false
        },
        "longitude": {
          "name": "longitude",
          "type": "numeric(11, 8)",
          "primaryKey": false,
          "notNull": false
        },
        "profileImageUrl": {
          "name": "profileImageUrl",
          "type": "varchar(500)",
          "primaryKey": false,
          "notNull": false
        },
        "isActive": {
          "name": "isActive",
          "type": "boolean",
          "primaryKey": false,
          "notNull": false,
          "default": true
        },
        "lastActiveAt": {
          "name": "lastActiveAt",
          "type": "timestamp with time zone",
          "primaryKey": false,
          "notNull": false
        },
        "createdAt": {
          "name": "createdAt",
          "type": "timestamp with time zone",
          "primaryKey": false,
          "notNull": true,
          "default": "CURRENT_TIMESTAMP"
        },
        "updatedAt": {
          "name": "updatedAt",
          "type": "timestamp with time zone",
          "primaryKey": false,
          "notNull": false
        }
      },
      "indexes": {
        "users_clerk_id_idx": {
          "name": "users_clerk_id_idx",
          "columns": [
            {
              "expression": "clerkId",
              "isExpression": false,
              "asc": true,
              "nulls": "last"
            }
          ],
          "isUnique": false,
          "concurrently": false,
          "method": "btree",
          "with": {}
        },
        "users_location_idx": {
          "name": "users_location_idx",
          "columns": [
            {
              "expression": "latitude",
              "isExpression": false,
              "asc": true,
              "nulls": "last"
            },
            {
              "expression": "longitude",
              "isExpression": false,
              "asc": true,
              "nulls": "last"
            }
          ],
          "isUnique": false,
          "concurrently": false,
          "method": "btree",
          "with": {}
        },
        "users_active_idx": {
          "name": "users_active_idx",
          "columns": [
            {
              "expression": "isActive",
              "isExpression": false,
              "asc": true,
              "nulls": "last"
            }
          ],
          "isUnique": false,
          "concurrently": false,
          "method": "btree",
          "with": {}
        }
      },
      "foreignKeys": {},
      "compositePrimaryKeys": {},
      "uniqueConstraints": {
        "bandsy_user_clerkId_unique": {
          "name": "bandsy_user_clerkId_unique",
          "nullsNotDistinct": false,
          "columns": [
            "clerkId"
          ]
        },
        "bandsy_user_username_unique": {
          "name": "bandsy_user_username_unique",
          "nullsNotDistinct": false,
          "columns": [
            "username"
          ]
        }
      },
      "policies": {},
      "checkConstraints": {},
      "isRLSEnabled": false
    }
  },
  "enums": {
    "public.group_role": {
      "name": "group_role",
      "schema": "public",
      "values": [
        "admin",
        "member"
      ]
    },
    "public.match_status": {
      "name": "match_status",
      "schema": "public",
      "values": [
        "pending",
        "accepted",
        "rejected"
      ]
    },
    "public.message_type": {
      "name": "message_type",
      "schema": "public",
      "values": [
        "text",
        "audio",
        "image"
      ]
    },
    "public.skill_level": {
      "name": "skill_level",
      "schema": "public",
      "values": [
        "beginner",
        "intermediate",
        "advanced",
        "professional"
      ]
    }
  },
  "schemas": {},
  "sequences": {},
  "roles": {},
  "policies": {},
  "views": {},
  "_meta": {
    "columns": {},
    "schemas": {},
    "tables": {}
  }
}